{
  "tournament": "Ligue 1 2025/26",
  "description": "Команды турнира Ligue 1",
  "teams": {
    "Анже": "Angers",
    "Брест": "Stade Brestois 29",
    "Гавр": "Le Havre",
    "Ланс": "Lens",
    "Лилль": "Lille",
    "Лион": "Lyon",
    "Лорьян": "Lorient",
    "Марсель": "Marseille",
    "Метц": "Metz",
    "Монако": "Monaco",
    "Нант": "Nantes",
    "Ницца": "Nice",
    "Осер": "Auxerre",
    "ПСЖ": "Paris Saint Germain",
    "Париж ФК": "Paris FC",
    "Ренн": "Rennes",
    "Страсбург": "Strasbourg",
    "Тулуза": "Toulouse"
  }
}